[{"externalId": "35805", "locationId": "9944", "location": "Sammen - Gr\u00f8nneviks\u00f8ren", "locationTopLevelName": "Bergen - M\u00f8llendalsveien 52", "serviceType": "WASHING_MACHINE", "serviceName": "vaskemaskiner", "unit": "transaksjon", "state": "OCCUPIED", "stateDescription": "okkupert", "lastSessionStart": 1649965774, "requiredFields": [], "freeFormQuestionInt": [], "pricing": [{"serviceType": "WASHING_MACHINE", "componentPriceObjects": [{"type": "UNIT_PRICE", "fullPriceString": "Pr. vaskesyklus: NOK 23.00", "priceString": "NOK 23.00", "costCents": 2300}]}], "tariffSetName": "default", "gps": {}, "reservable": "NOT_RESERVABLE", "reservations": [], "blockTimeSeconds": 900, "timeOfArrivalSeconds": 0, "checkoutTimeSeconds": 0, "startWithPredeterminedUsage": false, "optionalName": ""}, {"externalId": "35806", "locationId": "9944", "location": "Sammen - Gr\u00f8nneviks\u00f8ren", "locationTopLevelName": "Bergen - M\u00f8llendalsveien 52", "serviceType": "WASHING_MACHINE", "serviceName": "vaskemaskiner", "unit": "transaksjon", "state": "OCCUPIED", "stateDescription": "okkupert", "lastSessionStart": 1649965808, "requiredFields": [], "freeFormQuestionInt": [], "pricing": [{"serviceType": "WASHING_MACHINE", "componentPriceObjects": [{"type": "UNIT_PRICE", "fullPriceString": "Pr. vaskesyklus: NOK 23.00", "priceString": "NOK 23.00", "costCents": 2300}]}], "tariffSetName": "default", "gps": {}, "reservable": "NOT_RESERVABLE", "reservations": [], "blockTimeSeconds": 900, "timeOfArrivalSeconds": 0, "checkoutTimeSeconds": 0, "startWithPredeterminedUsage": false, "optionalName": ""}, {"externalId": "35807", "locationId": "9944", "location": "Sammen - Gr\u00f8nneviks\u00f8ren", "locationTopLevelName": "Bergen - M\u00f8llendalsveien 52", "serviceType": "WASHING_MACHINE", "serviceName": "vaskemaskiner", "unit": "transaksjon", "state": "OCCUPIED", "stateDescription": "okkupert", "lastSessionStart": 1649965416, "requiredFields": [], "freeFormQuestionInt": [], "pricing": [{"serviceType": "WASHING_MACHINE", "componentPriceObjects": [{"type": "UNIT_PRICE", "fullPriceString": "Pr. vaskesyklus: NOK 23.00", "priceString": "NOK 23.00", "costCents": 2300}]}], "tariffSetName": "default", "gps": {}, "reservable": "NOT_RESERVABLE", "reservations": [], "blockTimeSeconds": 900, "timeOfArrivalSeconds": 0, "checkoutTimeSeconds": 0, "startWithPredeterminedUsage": false, "optionalName": ""}, {"externalId": "35808", "locationId": "9944", "location": "Sammen - Gr\u00f8nneviks\u00f8ren", "locationTopLevelName": "Bergen - M\u00f8llendalsveien 52", "serviceType": "WASHING_MACHINE", "serviceName": "vaskemaskiner", "unit": "transaksjon", "state": "OCCUPIED", "stateDescription": "okkupert", "lastSessionStart": 1649965449, "requiredFields": [], "freeFormQuestionInt": [], "pricing": [{"serviceType": "WASHING_MACHINE", "componentPriceObjects": [{"type": "UNIT_PRICE", "fullPriceString": "Pr. vaskesyklus: NOK 23.00", "priceString": "NOK 23.00", "costCents": 2300}]}], "tariffSetName": "default", "gps": {}, "reservable": "NOT_RESERVABLE", "reservations": [], "blockTimeSeconds": 900, "timeOfArrivalSeconds": 0, "checkoutTimeSeconds": 0, "startWithPredeterminedUsage": false, "optionalName": ""}, {"externalId": "35809", "locationId": "9944", "location": "Sammen - Gr\u00f8nneviks\u00f8ren", "locationTopLevelName": "Bergen - M\u00f8llendalsveien 52", "serviceType": "WASHING_MACHINE", "serviceName": "vaskemaskiner", "unit": "transaksjon", "state": "OCCUPIED", "stateDescription": "okkupert", "lastSessionStart": 1649965479, "requiredFields": [], "freeFormQuestionInt": [], "pricing": [{"serviceType": "WASHING_MACHINE", "componentPriceObjects": [{"type": "UNIT_PRICE", "fullPriceString": "Pr. vaskesyklus: NOK 23.00", "priceString": "NOK 23.00", "costCents": 2300}]}], "tariffSetName": "default", "gps": {}, "reservable": "NOT_RESERVABLE", "reservations": [], "blockTimeSeconds": 900, "timeOfArrivalSeconds": 0, "checkoutTimeSeconds": 0, "startWithPredeterminedUsage": false, "optionalName": ""}, {"externalId": "35810", "locationId": "9944", "location": "Sammen - Gr\u00f8nneviks\u00f8ren", "locationTopLevelName": "Bergen - M\u00f8llendalsveien 52", "serviceType": "WASHING_MACHINE", "serviceName": "vaskemaskiner", "unit": "transaksjon", "state": "AVAILABLE", "stateDescription": "tilgjengelig", "requiredFields": [], "freeFormQuestionInt": [], "pricing": [{"serviceType": "WASHING_MACHINE", "componentPriceObjects": [{"type": "UNIT_PRICE", "fullPriceString": "Pr. vaskesyklus: NOK 23.00", "priceString": "NOK 23.00", "costCents": 2300}]}], "tariffSetName": "default", "gps": {}, "reservable": "NOT_RESERVABLE", "reservations": [], "blockTimeSeconds": 900, "timeOfArrivalSeconds": 0, "checkoutTimeSeconds": 0, "startWithPredeterminedUsage": false, "optionalName": ""}, {"externalId": "36081", "locationId": "9944", "location": "Sammen - Gr\u00f8nneviks\u00f8ren", "locationTopLevelName": "Bergen - M\u00f8llendalsveien 52", "serviceType": "WASHING_MACHINE", "serviceName": "vaskemaskiner", "unit": "transaksjon", "state": "AVAILABLE", "stateDescription": "tilgjengelig", "requiredFields": [], "freeFormQuestionInt": [], "pricing": [{"serviceType": "WASHING_MACHINE", "componentPriceObjects": [{"type": "UNIT_PRICE", "fullPriceString": "Pr. vaskesyklus: NOK 23.00", "priceString": "NOK 23.00", "costCents": 2300}]}], "tariffSetName": "default", "gps": {}, "reservable": "NOT_RESERVABLE", "reservations": [], "blockTimeSeconds": 900, "timeOfArrivalSeconds": 0, "checkoutTimeSeconds": 0, "startWithPredeterminedUsage": false, "optionalName": ""}, {"externalId": "36082", "locationId": "9944", "location": "Sammen - Gr\u00f8nneviks\u00f8ren", "locationTopLevelName": "Bergen - M\u00f8llendalsveien 52", "serviceType": "WASHING_MACHINE", "serviceName": "vaskemaskiner", "unit": "transaksjon", "state": "AVAILABLE", "stateDescription": "tilgjengelig", "requiredFields": [], "freeFormQuestionInt": [], "pricing": [{"serviceType": "WASHING_MACHINE", "componentPriceObjects": [{"type": "UNIT_PRICE", "fullPriceString": "Pr. vaskesyklus: NOK 23.00", "priceString": "NOK 23.00", "costCents": 2300}]}], "tariffSetName": "default", "gps": {}, "reservable": "NOT_RESERVABLE", "reservations": [], "blockTimeSeconds": 900, "timeOfArrivalSeconds": 0, "checkoutTimeSeconds": 0, "startWithPredeterminedUsage": false, "optionalName": ""}, {"externalId": "36083", "locationId": "9944", "location": "Sammen - Gr\u00f8nneviks\u00f8ren", "locationTopLevelName": "Bergen - M\u00f8llendalsveien 52", "serviceType": "WASHING_MACHINE", "serviceName": "vaskemaskiner", "unit": "transaksjon", "state": "AVAILABLE", "stateDescription": "tilgjengelig", "requiredFields": [], "freeFormQuestionInt": [], "pricing": [{"serviceType": "WASHING_MACHINE", "componentPriceObjects": [{"type": "UNIT_PRICE", "fullPriceString": "Pr. vaskesyklus: NOK 23.00", "priceString": "NOK 23.00", "costCents": 2300}]}], "tariffSetName": "default", "gps": {}, "reservable": "NOT_RESERVABLE", "reservations": [], "blockTimeSeconds": 900, "timeOfArrivalSeconds": 0, "checkoutTimeSeconds": 0, "startWithPredeterminedUsage": false, "optionalName": ""}, {"externalId": "36084", "locationId": "9944", "location": "Sammen - Gr\u00f8nneviks\u00f8ren", "locationTopLevelName": "Bergen - M\u00f8llendalsveien 52", "serviceType": "WASHING_MACHINE", "serviceName": "vaskemaskiner", "unit": "transaksjon", "state": "AVAILABLE", "stateDescription": "tilgjengelig", "requiredFields": [], "freeFormQuestionInt": [], "pricing": [{"serviceType": "WASHING_MACHINE", "componentPriceObjects": [{"type": "UNIT_PRICE", "fullPriceString": "Pr. vaskesyklus: NOK 23.00", "priceString": "NOK 23.00", "costCents": 2300}]}], "tariffSetName": "default", "gps": {}, "reservable": "NOT_RESERVABLE", "reservations": [], "blockTimeSeconds": 900, "timeOfArrivalSeconds": 0, "checkoutTimeSeconds": 0, "startWithPredeterminedUsage": false, "optionalName": ""}, {"externalId": "36085", "locationId": "9944", "location": "Sammen - Gr\u00f8nneviks\u00f8ren", "locationTopLevelName": "Bergen - M\u00f8llendalsveien 52", "serviceType": "WASHING_MACHINE", "serviceName": "vaskemaskiner", "unit": "transaksjon", "state": "AVAILABLE", "stateDescription": "tilgjengelig", "requiredFields": [], "freeFormQuestionInt": [], "pricing": [{"serviceType": "WASHING_MACHINE", "componentPriceObjects": [{"type": "UNIT_PRICE", "fullPriceString": "Pr. vaskesyklus: NOK 23.00", "priceString": "NOK 23.00", "costCents": 2300}]}], "tariffSetName": "default", "gps": {}, "reservable": "NOT_RESERVABLE", "reservations": [], "blockTimeSeconds": 900, "timeOfArrivalSeconds": 0, "checkoutTimeSeconds": 0, "startWithPredeterminedUsage": false, "optionalName": ""}, {"externalId": "36086", "locationId": "9944", "location": "Sammen - Gr\u00f8nneviks\u00f8ren", "locationTopLevelName": "Bergen - M\u00f8llendalsveien 52", "serviceType": "WASHING_MACHINE", "serviceName": "vaskemaskiner", "unit": "transaksjon", "state": "FAULTED", "stateDescription": "ikke tilgjengelig", "requiredFields": [], "freeFormQuestionInt": [], "pricing": [{"serviceType": "WASHING_MACHINE", "componentPriceObjects": [{"type": "UNIT_PRICE", "fullPriceString": "Pr. vaskesyklus: NOK 23.00", "priceString": "NOK 23.00", "costCents": 2300}]}], "tariffSetName": "default", "gps": {}, "reservable": "NOT_RESERVABLE", "reservations": [], "blockTimeSeconds": 900, "timeOfArrivalSeconds": 0, "checkoutTimeSeconds": 0, "startWithPredeterminedUsage": false}, {"externalId": "36183", "locationId": "9944", "location": "Sammen - Gr\u00f8nneviks\u00f8ren", "locationTopLevelName": "Bergen - M\u00f8llendalsveien 52", "serviceType": "WASHING_MACHINE", "serviceName": "vaskemaskiner", "unit": "transaksjon", "state": "AVAILABLE", "stateDescription": "tilgjengelig", "requiredFields": [], "freeFormQuestionInt": [], "pricing": [{"serviceType": "WASHING_MACHINE", "componentPriceObjects": [{"type": "UNIT_PRICE", "fullPriceString": "Pr. vaskesyklus: NOK 23.00", "priceString": "NOK 23.00", "costCents": 2300}]}], "tariffSetName": "default", "gps": {}, "reservable": "NOT_RESERVABLE", "reservations": [], "blockTimeSeconds": 900, "timeOfArrivalSeconds": 0, "checkoutTimeSeconds": 0, "startWithPredeterminedUsage": false, "optionalName": ""}, {"externalId": "36184", "locationId": "9944", "location": "Sammen - Gr\u00f8nneviks\u00f8ren", "locationTopLevelName": "Bergen - M\u00f8llendalsveien 52", "serviceType": "WASHING_MACHINE", "serviceName": "vaskemaskiner", "unit": "transaksjon", "state": "AVAILABLE", "stateDescription": "tilgjengelig", "requiredFields": [], "freeFormQuestionInt": [], "pricing": [{"serviceType": "WASHING_MACHINE", "componentPriceObjects": [{"type": "UNIT_PRICE", "fullPriceString": "Pr. vaskesyklus: NOK 23.00", "priceString": "NOK 23.00", "costCents": 2300}]}], "tariffSetName": "default", "gps": {}, "reservable": "NOT_RESERVABLE", "reservations": [], "blockTimeSeconds": 900, "timeOfArrivalSeconds": 0, "checkoutTimeSeconds": 0, "startWithPredeterminedUsage": false, "optionalName": ""}, {"externalId": "36185", "locationId": "9944", "location": "Sammen - Gr\u00f8nneviks\u00f8ren", "locationTopLevelName": "Bergen - M\u00f8llendalsveien 52", "serviceType": "WASHING_MACHINE", "serviceName": "vaskemaskiner", "unit": "transaksjon", "state": "AVAILABLE", "stateDescription": "tilgjengelig", "requiredFields": [], "freeFormQuestionInt": [], "pricing": [{"serviceType": "WASHING_MACHINE", "componentPriceObjects": [{"type": "UNIT_PRICE", "fullPriceString": "Pr. vaskesyklus: NOK 23.00", "priceString": "NOK 23.00", "costCents": 2300}]}], "tariffSetName": "default", "gps": {}, "reservable": "NOT_RESERVABLE", "reservations": [], "blockTimeSeconds": 900, "timeOfArrivalSeconds": 0, "checkoutTimeSeconds": 0, "startWithPredeterminedUsage": false, "optionalName": ""}, {"externalId": "36186", "locationId": "9944", "location": "Sammen - Gr\u00f8nneviks\u00f8ren", "locationTopLevelName": "Bergen - M\u00f8llendalsveien 52", "serviceType": "WASHING_MACHINE", "serviceName": "vaskemaskiner", "unit": "transaksjon", "state": "AVAILABLE", "stateDescription": "tilgjengelig", "requiredFields": [], "freeFormQuestionInt": [], "pricing": [{"serviceType": "WASHING_MACHINE", "componentPriceObjects": [{"type": "UNIT_PRICE", "fullPriceString": "Pr. vaskesyklus: NOK 23.00", "priceString": "NOK 23.00", "costCents": 2300}]}], "tariffSetName": "default", "gps": {}, "reservable": "NOT_RESERVABLE", "reservations": [], "blockTimeSeconds": 900, "timeOfArrivalSeconds": 0, "checkoutTimeSeconds": 0, "startWithPredeterminedUsage": false, "optionalName": ""}, {"externalId": "36187", "locationId": "9944", "location": "Sammen - Gr\u00f8nneviks\u00f8ren", "locationTopLevelName": "Bergen - M\u00f8llendalsveien 52", "serviceType": "WASHING_MACHINE", "serviceName": "vaskemaskiner", "unit": "transaksjon", "state": "AVAILABLE", "stateDescription": "tilgjengelig", "requiredFields": [], "freeFormQuestionInt": [], "pricing": [{"serviceType": "WASHING_MACHINE", "componentPriceObjects": [{"type": "UNIT_PRICE", "fullPriceString": "Pr. vaskesyklus: NOK 23.00", "priceString": "NOK 23.00", "costCents": 2300}]}], "tariffSetName": "default", "gps": {}, "reservable": "NOT_RESERVABLE", "reservations": [], "blockTimeSeconds": 900, "timeOfArrivalSeconds": 0, "checkoutTimeSeconds": 0, "startWithPredeterminedUsage": false, "optionalName": ""}, {"externalId": "36188", "locationId": "9944", "location": "Sammen - Gr\u00f8nneviks\u00f8ren", "locationTopLevelName": "Bergen - M\u00f8llendalsveien 52", "serviceType": "WASHING_MACHINE", "serviceName": "vaskemaskiner", "unit": "transaksjon", "state": "AVAILABLE", "stateDescription": "tilgjengelig", "requiredFields": [], "freeFormQuestionInt": [], "pricing": [{"serviceType": "WASHING_MACHINE", "componentPriceObjects": [{"type": "UNIT_PRICE", "fullPriceString": "Pr. vaskesyklus: NOK 23.00", "priceString": "NOK 23.00", "costCents": 2300}]}], "tariffSetName": "default", "gps": {}, "reservable": "NOT_RESERVABLE", "reservations": [], "blockTimeSeconds": 900, "timeOfArrivalSeconds": 0, "checkoutTimeSeconds": 0, "startWithPredeterminedUsage": false, "optionalName": ""}]